setup.py
tests/__init__.py
tests/base.py
tests/test_bus.py
tests/test_version.py
tornado_eventbus/__init__.py
tornado_eventbus/bus.py
tornado_eventbus/version.py
tornado_eventbus.egg-info/PKG-INFO
tornado_eventbus.egg-info/SOURCES.txt
tornado_eventbus.egg-info/dependency_links.txt
tornado_eventbus.egg-info/entry_points.txt
tornado_eventbus.egg-info/requires.txt
tornado_eventbus.egg-info/top_level.txt