Metadata-Version: 1.1
Name: tornado-eventbus
Version: 0.2.0
Summary: tornado-eventbus is an asynchronous event bus for tornado applications.
Home-page: https://github.com/thumby/tornado-eventbus
Author: Bernardo Heynemann
Author-email: heynemann@gmail.com
License: MIT
Keywords: tornado python asynchronous async event bus
Platform: UNKNOWN
Classifier: Development Status :: 4 - Beta
Classifier: Intended Audience :: Developers
Classifier: License :: OSI Approved :: MIT License
Classifier: Natural Language :: English
Classifier: Operating System :: Unix
Classifier: Programming Language :: Python :: 2.7
Classifier: Programming Language :: Python :: 3.4
Classifier: Programming Language :: Python :: Implementation :: PyPy
Classifier: Operating System :: OS Independent
